[
  {
    "timestamp": "2026-07-02T12:00:36.358703+00:00",
    "timestamp_brt": "02/07/2026 09:00",
    "posted": 0,
    "failed": 0,
    "retried": 0,
    "skipped": 0,
    "total_pending": 0,
    "replies": 0,
    "details": []
  },
  {
    "timestamp": "2026-07-02T11:45:27.537777+00:00",
    "timestamp_brt": "02/07/2026 08:45",
    "posted": 0,
    "failed": 0,
    "retried": 0,
    "skipped": 0,
    "total_pending": 0,
    "replies": 0,
    "details": []
  },
  {
    "timestamp": "2026-07-02T11:30:34.360763+00:00",
    "timestamp_brt": "02/07/2026 08:30",
    "posted": 0,
    "failed": 0,
    "retried": 0,
    "skipped": 0,
    "total_pending": 0,
    "replies": 0,
    "details": []
  },
  {
    "timestamp": "2026-07-02T11:15:28.483764+00:00",
    "timestamp_brt": "02/07/2026 08:15",
    "posted": 0,
    "failed": 0,
    "retried": 0,
    "skipped": 0,
    "total_pending": 0,
    "replies": 0,
    "details": []
  },
  {
    "timestamp": "2026-07-02T11:00:36.332335+00:00",
    "timestamp_brt": "02/07/2026 08:00",
    "posted": 0,
    "failed": 0,
    "retried": 0,
    "skipped": 0,
    "total_pending": 0,
    "replies": 0,
    "details": []
  },
  {
    "timestamp": "2026-07-02T10:45:21.976622+00:00",
    "timestamp_brt": "02/07/2026 07:45",
    "posted": 0,
    "failed": 0,
    "retried": 0,
    "skipped": 0,
    "total_pending": 0,
    "replies": 0,
    "details": []
  },
  {
    "timestamp": "2026-07-02T10:30:28.606330+00:00",
    "timestamp_brt": "02/07/2026 07:30",
    "posted": 0,
    "failed": 0,
    "retried": 0,
    "skipped": 0,
    "total_pending": 0,
    "replies": 0,
    "details": []
  },
  {
    "timestamp": "2026-07-02T10:15:25.948901+00:00",
    "timestamp_brt": "02/07/2026 07:15",
    "posted": 0,
    "failed": 0,
    "retried": 0,
    "skipped": 0,
    "total_pending": 0,
    "replies": 0,
    "details": []
  },
  {
    "timestamp": "2026-07-02T10:00:33.520204+00:00",
    "timestamp_brt": "02/07/2026 07:00",
    "posted": 0,
    "failed": 0,
    "retried": 0,
    "skipped": 0,
    "total_pending": 0,
    "replies": 0,
    "details": []
  },
  {
    "timestamp": "2026-07-02T09:45:23.982525+00:00",
    "timestamp_brt": "02/07/2026 06:45",
    "posted": 0,
    "failed": 0,
    "retried": 0,
    "skipped": 0,
    "total_pending": 0,
    "replies": 0,
    "details": []
  },
  {
    "timestamp": "2026-07-02T09:30:32.306596+00:00",
    "timestamp_brt": "02/07/2026 06:30",
    "posted": 0,
    "failed": 0,
    "retried": 0,
    "skipped": 0,
    "total_pending": 0,
    "replies": 0,
    "details": []
  },
  {
    "timestamp": "2026-07-02T09:15:25.627773+00:00",
    "timestamp_brt": "02/07/2026 06:15",
    "posted": 0,
    "failed": 0,
    "retried": 0,
    "skipped": 0,
    "total_pending": 0,
    "replies": 0,
    "details": []
  },
  {
    "timestamp": "2026-07-02T09:00:41.283899+00:00",
    "timestamp_brt": "02/07/2026 06:00",
    "posted": 0,
    "failed": 0,
    "retried": 0,
    "skipped": 0,
    "total_pending": 0,
    "replies": 0,
    "details": []
  },
  {
    "timestamp": "2026-07-02T08:45:27.839403+00:00",
    "timestamp_brt": "02/07/2026 05:45",
    "posted": 0,
    "failed": 0,
    "retried": 0,
    "skipped": 0,
    "total_pending": 0,
    "replies": 0,
    "details": []
  },
  {
    "timestamp": "2026-07-02T08:30:31.623074+00:00",
    "timestamp_brt": "02/07/2026 05:30",
    "posted": 0,
    "failed": 0,
    "retried": 0,
    "skipped": 0,
    "total_pending": 0,
    "replies": 0,
    "details": []
  },
  {
    "timestamp": "2026-07-02T08:15:24.190270+00:00",
    "timestamp_brt": "02/07/2026 05:15",
    "posted": 0,
    "failed": 0,
    "retried": 0,
    "skipped": 0,
    "total_pending": 0,
    "replies": 0,
    "details": []
  },
  {
    "timestamp": "2026-07-02T08:00:35.301125+00:00",
    "timestamp_brt": "02/07/2026 05:00",
    "posted": 0,
    "failed": 0,
    "retried": 0,
    "skipped": 0,
    "total_pending": 0,
    "replies": 0,
    "details": []
  },
  {
    "timestamp": "2026-07-02T07:45:23.423282+00:00",
    "timestamp_brt": "02/07/2026 04:45",
    "posted": 0,
    "failed": 0,
    "retried": 0,
    "skipped": 0,
    "total_pending": 0,
    "replies": 0,
    "details": []
  },
  {
    "timestamp": "2026-07-02T07:30:30.744678+00:00",
    "timestamp_brt": "02/07/2026 04:30",
    "posted": 0,
    "failed": 0,
    "retried": 0,
    "skipped": 0,
    "total_pending": 0,
    "replies": 0,
    "details": []
  },
  {
    "timestamp": "2026-07-02T07:15:24.322598+00:00",
    "timestamp_brt": "02/07/2026 04:15",
    "posted": 0,
    "failed": 0,
    "retried": 0,
    "skipped": 0,
    "total_pending": 0,
    "replies": 0,
    "details": []
  },
  {
    "timestamp": "2026-07-02T07:00:37.210229+00:00",
    "timestamp_brt": "02/07/2026 04:00",
    "posted": 0,
    "failed": 0,
    "retried": 0,
    "skipped": 0,
    "total_pending": 0,
    "replies": 0,
    "details": []
  },
  {
    "timestamp": "2026-07-02T06:45:28.132520+00:00",
    "timestamp_brt": "02/07/2026 03:45",
    "posted": 0,
    "failed": 0,
    "retried": 0,
    "skipped": 0,
    "total_pending": 0,
    "replies": 0,
    "details": []
  },
  {
    "timestamp": "2026-07-02T06:30:27.764017+00:00",
    "timestamp_brt": "02/07/2026 03:30",
    "posted": 0,
    "failed": 0,
    "retried": 0,
    "skipped": 0,
    "total_pending": 0,
    "replies": 0,
    "details": []
  },
  {
    "timestamp": "2026-07-02T06:15:22.939271+00:00",
    "timestamp_brt": "02/07/2026 03:15",
    "posted": 0,
    "failed": 0,
    "retried": 0,
    "skipped": 0,
    "total_pending": 0,
    "replies": 0,
    "details": []
  },
  {
    "timestamp": "2026-07-02T06:00:40.956929+00:00",
    "timestamp_brt": "02/07/2026 03:00",
    "posted": 0,
    "failed": 0,
    "retried": 0,
    "skipped": 0,
    "total_pending": 0,
    "replies": 0,
    "details": []
  },
  {
    "timestamp": "2026-07-02T05:45:26.177929+00:00",
    "timestamp_brt": "02/07/2026 02:45",
    "posted": 0,
    "failed": 0,
    "retried": 0,
    "skipped": 0,
    "total_pending": 0,
    "replies": 0,
    "details": []
  },
  {
    "timestamp": "2026-07-02T05:30:30.845203+00:00",
    "timestamp_brt": "02/07/2026 02:30",
    "posted": 0,
    "failed": 0,
    "retried": 0,
    "skipped": 0,
    "total_pending": 0,
    "replies": 0,
    "details": []
  },
  {
    "timestamp": "2026-07-02T05:15:22.440191+00:00",
    "timestamp_brt": "02/07/2026 02:15",
    "posted": 0,
    "failed": 0,
    "retried": 0,
    "skipped": 0,
    "total_pending": 0,
    "replies": 0,
    "details": []
  },
  {
    "timestamp": "2026-07-02T05:00:34.056153+00:00",
    "timestamp_brt": "02/07/2026 02:00",
    "posted": 0,
    "failed": 0,
    "retried": 0,
    "skipped": 0,
    "total_pending": 0,
    "replies": 0,
    "details": []
  },
  {
    "timestamp": "2026-07-02T04:45:24.473814+00:00",
    "timestamp_brt": "02/07/2026 01:45",
    "posted": 0,
    "failed": 0,
    "retried": 0,
    "skipped": 0,
    "total_pending": 0,
    "replies": 0,
    "details": []
  },
  {
    "timestamp": "2026-07-02T04:30:32.091908+00:00",
    "timestamp_brt": "02/07/2026 01:30",
    "posted": 0,
    "failed": 0,
    "retried": 0,
    "skipped": 0,
    "total_pending": 0,
    "replies": 0,
    "details": []
  },
  {
    "timestamp": "2026-07-02T04:15:21.547568+00:00",
    "timestamp_brt": "02/07/2026 01:15",
    "posted": 0,
    "failed": 0,
    "retried": 0,
    "skipped": 0,
    "total_pending": 0,
    "replies": 0,
    "details": []
  },
  {
    "timestamp": "2026-07-02T04:00:36.208208+00:00",
    "timestamp_brt": "02/07/2026 01:00",
    "posted": 0,
    "failed": 0,
    "retried": 0,
    "skipped": 0,
    "total_pending": 0,
    "replies": 0,
    "details": []
  },
  {
    "timestamp": "2026-07-02T03:45:21.559886+00:00",
    "timestamp_brt": "02/07/2026 00:45",
    "posted": 0,
    "failed": 0,
    "retried": 0,
    "skipped": 0,
    "total_pending": 0,
    "replies": 0,
    "details": []
  },
  {
    "timestamp": "2026-07-02T03:30:35.607382+00:00",
    "timestamp_brt": "02/07/2026 00:30",
    "posted": 0,
    "failed": 0,
    "retried": 0,
    "skipped": 0,
    "total_pending": 0,
    "replies": 0,
    "details": []
  },
  {
    "timestamp": "2026-07-02T03:15:25.721085+00:00",
    "timestamp_brt": "02/07/2026 00:15",
    "posted": 0,
    "failed": 0,
    "retried": 0,
    "skipped": 0,
    "total_pending": 0,
    "replies": 0,
    "details": []
  },
  {
    "timestamp": "2026-07-02T03:00:35.181790+00:00",
    "timestamp_brt": "02/07/2026 00:00",
    "posted": 0,
    "failed": 0,
    "retried": 0,
    "skipped": 0,
    "total_pending": 0,
    "replies": 0,
    "details": []
  },
  {
    "timestamp": "2026-07-02T02:45:24.795954+00:00",
    "timestamp_brt": "01/07/2026 23:45",
    "posted": 0,
    "failed": 0,
    "retried": 0,
    "skipped": 0,
    "total_pending": 0,
    "replies": 0,
    "details": []
  },
  {
    "timestamp": "2026-07-02T02:30:36.782527+00:00",
    "timestamp_brt": "01/07/2026 23:30",
    "posted": 0,
    "failed": 0,
    "retried": 0,
    "skipped": 0,
    "total_pending": 0,
    "replies": 0,
    "details": []
  },
  {
    "timestamp": "2026-07-02T02:15:23.470456+00:00",
    "timestamp_brt": "01/07/2026 23:15",
    "posted": 0,
    "failed": 0,
    "retried": 0,
    "skipped": 0,
    "total_pending": 0,
    "replies": 0,
    "details": []
  },
  {
    "timestamp": "2026-07-02T02:00:40.684230+00:00",
    "timestamp_brt": "01/07/2026 23:00",
    "posted": 0,
    "failed": 0,
    "retried": 0,
    "skipped": 0,
    "total_pending": 0,
    "replies": 0,
    "details": []
  },
  {
    "timestamp": "2026-07-02T01:45:24.203871+00:00",
    "timestamp_brt": "01/07/2026 22:45",
    "posted": 0,
    "failed": 0,
    "retried": 0,
    "skipped": 0,
    "total_pending": 0,
    "replies": 0,
    "details": []
  },
  {
    "timestamp": "2026-07-02T01:30:28.672827+00:00",
    "timestamp_brt": "01/07/2026 22:30",
    "posted": 0,
    "failed": 0,
    "retried": 0,
    "skipped": 0,
    "total_pending": 0,
    "replies": 0,
    "details": []
  },
  {
    "timestamp": "2026-07-02T01:15:23.742507+00:00",
    "timestamp_brt": "01/07/2026 22:15",
    "posted": 0,
    "failed": 0,
    "retried": 0,
    "skipped": 0,
    "total_pending": 0,
    "replies": 0,
    "details": []
  },
  {
    "timestamp": "2026-07-02T01:00:31.753389+00:00",
    "timestamp_brt": "01/07/2026 22:00",
    "posted": 0,
    "failed": 0,
    "retried": 0,
    "skipped": 0,
    "total_pending": 0,
    "replies": 0,
    "details": []
  },
  {
    "timestamp": "2026-07-02T00:45:25.984973+00:00",
    "timestamp_brt": "01/07/2026 21:45",
    "posted": 0,
    "failed": 0,
    "retried": 0,
    "skipped": 0,
    "total_pending": 0,
    "replies": 0,
    "details": []
  },
  {
    "timestamp": "2026-07-02T00:30:26.019006+00:00",
    "timestamp_brt": "01/07/2026 21:30",
    "posted": 0,
    "failed": 0,
    "retried": 0,
    "skipped": 0,
    "total_pending": 0,
    "replies": 1,
    "details": []
  },
  {
    "timestamp": "2026-07-02T00:15:21.408375+00:00",
    "timestamp_brt": "01/07/2026 21:15",
    "posted": 0,
    "failed": 0,
    "retried": 0,
    "skipped": 0,
    "total_pending": 0,
    "replies": 0,
    "details": []
  },
  {
    "timestamp": "2026-07-02T00:00:34.084765+00:00",
    "timestamp_brt": "01/07/2026 21:00",
    "posted": 0,
    "failed": 0,
    "retried": 0,
    "skipped": 0,
    "total_pending": 0,
    "replies": 0,
    "details": []
  },
  {
    "timestamp": "2026-07-01T23:45:21.905854+00:00",
    "timestamp_brt": "01/07/2026 20:45",
    "posted": 0,
    "failed": 0,
    "retried": 0,
    "skipped": 0,
    "total_pending": 0,
    "replies": 0,
    "details": []
  }
]